nyaggle/__init__.py
nyaggle/environment.py
nyaggle/version.py
nyaggle/ensemble/__init__.py
nyaggle/ensemble/averaging.py
nyaggle/ensemble/common.py
nyaggle/ensemble/stacking.py
nyaggle/experiment/__init__.py
nyaggle/experiment/auto_prep.py
nyaggle/experiment/experiment.py
nyaggle/experiment/hyperparameter_tuner.py
nyaggle/experiment/run.py
nyaggle/feature/__init__.py
nyaggle/feature/base.py
nyaggle/feature/groupby.py
nyaggle/feature/category_encoder/__init__.py
nyaggle/feature/category_encoder/target_encoder.py
nyaggle/feature/nlp/__init__.py
nyaggle/feature/nlp/bert.py
nyaggle/feature_store/__init__.py
nyaggle/feature_store/feature_store.py
nyaggle/hyper_parameters/__init__.py
nyaggle/hyper_parameters/catboost.py
nyaggle/hyper_parameters/lightgbm.py
nyaggle/hyper_parameters/parameters.py
nyaggle/hyper_parameters/xgboost.py
nyaggle/testing/__init__.py
nyaggle/testing/util.py
nyaggle/util/__init__.py
nyaggle/util/plot_importance.py
nyaggle/util/submission.py
nyaggle/util/traits.py
nyaggle/validation/__init__.py
nyaggle/validation/adversarial_validate.py
nyaggle/validation/cross_validate.py
nyaggle/validation/split.py
tests/__init__.py
tests/conftest.py
nyaggle-0.1.6.dist-info/LICENSE
nyaggle-0.1.6.dist-info/METADATA
nyaggle-0.1.6.dist-info/WHEEL
nyaggle-0.1.6.dist-info/top_level.txt
nyaggle-0.1.6.dist-info/RECORD
