Metadata-Version: 2.1
Name: nyaggle
Version: 0.1.6
Summary: Code for Kaggle and Offline Competitions.
Home-page: https://github.com/nyanp/nyaggle
Author: nyanp
Author-email: Noumi.Taiga@gmail.com
License: MIT
Keywords: nyaggle kaggle
Classifier: License :: OSI Approved :: BSD License
Classifier: Programming Language :: Python :: 3.8
Classifier: Programming Language :: Python :: 3.9
Classifier: Programming Language :: Python :: 3.10
Classifier: Programming Language :: Python :: 3.11
License-File: LICENSE
Requires-Dist: category-encoders
Requires-Dist: matplotlib
Requires-Dist: more-itertools
Requires-Dist: numpy
Requires-Dist: optuna (>=1.0.0)
Requires-Dist: pandas
Requires-Dist: pyarrow
Requires-Dist: seaborn
Requires-Dist: scikit-learn
Requires-Dist: tqdm
Requires-Dist: transformers (>=2.3.0)
Provides-Extra: all
Requires-Dist: catboost (>=0.17) ; extra == 'all'
Requires-Dist: lightgbm ; extra == 'all'
Requires-Dist: xgboost ; extra == 'all'
Requires-Dist: torch ; extra == 'all'
Requires-Dist: mlflow ; extra == 'all'
